cbrtopdf/constants.py
cbrtopdf/logger.py
cbrtopdf/main.py
cbrtopdf-0.1.0.dist-info/METADATA
cbrtopdf-0.1.0.dist-info/WHEEL
cbrtopdf-0.1.0.dist-info/entry_points.txt
cbrtopdf-0.1.0.dist-info/licenses/LICENSE
cbrtopdf-0.1.0.dist-info/RECORD
