Metadata-Version: 2.4
Name: cbrtopdf
Version: 0.1.0
Summary: A command-line tool to convert CBR (Comic Book RAR) files into PDF
License: MIT
License-File: LICENSE
Author: JeremyAndress
Author-email: jeremysilvasilva@gmail.com
Requires-Python: >=3.10
Classifier: License :: OSI Approved :: MIT License
Classifier: Programming Language :: Python :: 3
Classifier: Programming Language :: Python :: 3.10
Classifier: Programming Language :: Python :: 3.11
Classifier: Programming Language :: Python :: 3.12
Classifier: Programming Language :: Python :: 3.13
Classifier: Programming Language :: Python :: 3.14
Requires-Dist: pikepdf (==10.0.3)
Requires-Dist: pillow (==12.0.0)
Requires-Dist: typer (==0.20.1)
